salt_nornir/__init__.py
salt_nornir/loader.py
salt_nornir/modules/__init__.py
salt_nornir/modules/nornir_proxy_execution_module.py
salt_nornir/netbox_utils.py
salt_nornir/pillar/__init__.py
salt_nornir/pillar/salt_nornir_netbox.py
salt_nornir/proxy/__init__.py
salt_nornir/proxy/nornir_proxy_module.py
salt_nornir/pydantic_models.py
salt_nornir/runners/__init__.py
salt_nornir/runners/nornir_proxy_runner_module.py
salt_nornir/salt_nornir_robot.py
salt_nornir/salt_nornir_shell_models.py
salt_nornir/states/__init__.py
salt_nornir/states/nornir_proxy_state_module.py
salt_nornir/utils.py
salt_nornir-0.21.1.dist-info/entry_points.txt
salt_nornir-0.21.1.dist-info/LICENSE
salt_nornir-0.21.1.dist-info/METADATA
salt_nornir-0.21.1.dist-info/WHEEL
salt_nornir-0.21.1.dist-info/RECORD
