Metadata-Version: 2.1
Name: salt-nornir
Version: 0.21.1
Summary: Salt-Nornir Proxy Minion SaltStack Modules
Home-page: https://github.com/dmulyalin/salt-nornir
License: MIT
Keywords: Nornir,SaltStack,salt-extension
Author: Denis Mulyalin
Author-email: d.mulyalin@gmail.com
Maintainer: Denis Mulyalin
Maintainer-email: d.mulyalin@gmail.com
Requires-Python: >=3.8,<4.0
Classifier: License :: OSI Approved :: MIT License
Classifier: Operating System :: POSIX :: Linux
Classifier: Programming Language :: Python :: 3
Classifier: Programming Language :: Python :: 3.8
Classifier: Programming Language :: Python :: 3.9
Classifier: Programming Language :: Python :: 3.10
Classifier: Programming Language :: Python :: 3.11
Classifier: Programming Language :: Python :: 3.10
Classifier: Programming Language :: Python :: 3.7
Classifier: Programming Language :: Python :: 3.8
Classifier: Programming Language :: Python :: 3.9
Classifier: Topic :: Utilities
Provides-Extra: dataprocessor
Provides-Extra: docs
Provides-Extra: gnmi
Provides-Extra: napalm
Provides-Extra: netbox
Provides-Extra: netconf
Provides-Extra: netmiko
Provides-Extra: prodmaxmaster
Provides-Extra: prodmaxminion
Provides-Extra: prodminmaster
Provides-Extra: prodminminion
Provides-Extra: pyats
Provides-Extra: restconf
Provides-Extra: robot
Provides-Extra: scrapli
Requires-Dist: N2G (>=0.3.0,<0.4.0) ; extra == "prodmaxmaster"
Requires-Dist: Sphinx (==4.3.0) ; extra == "docs"
Requires-Dist: cerberus (==1.3.5) ; extra == "prodmaxminion" or extra == "dataprocessor"
Requires-Dist: diskcache (==5.6.3) ; extra == "prodmaxmaster" or extra == "prodmaxminion" or extra == "netbox"
Requires-Dist: dnspython (==2.4.2) ; (python_version >= "3.8" and python_version < "4.0") and (extra == "prodmaxminion")
Requires-Dist: genie[full] (==23.11) ; (sys_platform != "win32") and (extra == "prodmaxminion" or extra == "pyats")
Requires-Dist: jinja2 (==3.1.3) ; extra == "prodminminion" or extra == "prodmaxminion"
Requires-Dist: jmespath (==1.0.1) ; extra == "prodmaxminion" or extra == "dataprocessor"
Requires-Dist: lxml (>=4.9.3,<5.1.0) ; extra == "dataprocessor"
Requires-Dist: napalm (==4.1.0) ; extra == "prodmaxminion" or extra == "napalm"
Requires-Dist: ncclient (==0.6.15) ; extra == "prodminminion" or extra == "prodmaxminion" or extra == "netconf"
Requires-Dist: netmiko (==4.3.0) ; extra == "prodminminion" or extra == "prodmaxminion" or extra == "netmiko"
Requires-Dist: nornir (>=3.3.0,<=3.4.1)
Requires-Dist: nornir-napalm (==0.4.0) ; extra == "prodmaxminion" or extra == "napalm"
Requires-Dist: nornir-netmiko (==1.0.1) ; extra == "prodminminion" or extra == "prodmaxminion" or extra == "netmiko"
Requires-Dist: nornir-scrapli (==2023.7.30) ; extra == "prodmaxminion"
Requires-Dist: nornir_salt (>=0.21.0,<0.22.0)
Requires-Dist: ntc-templates (==4.1.0) ; extra == "prodmaxminion" or extra == "dataprocessor"
Requires-Dist: paramiko (==3.4.0) ; extra == "prodminminion" or extra == "prodmaxminion"
Requires-Dist: picle (>=0.2.0,<0.3.0) ; extra == "prodmaxmaster"
Requires-Dist: psutil (>=5.8,<6)
Requires-Dist: puresnmp[crypto] (==2.0.0) ; extra == "prodmaxminion"
Requires-Dist: pyats[full] (==23.11) ; (sys_platform != "win32") and (extra == "prodmaxminion" or extra == "pyats")
Requires-Dist: pydantic (>=1.10.2,<=2.5.3)
Requires-Dist: pygnmi (==0.8.13) ; extra == "prodmaxminion" or extra == "gnmi"
Requires-Dist: pynetbox (==7.4.1) ; extra == "prodmaxmaster" or extra == "prodmaxminion" or extra == "netbox"
Requires-Dist: pythonping (==1.1.4) ; extra == "prodmaxminion"
Requires-Dist: pyyaml (==6.0.1) ; extra == "prodmaxminion" or extra == "dataprocessor"
Requires-Dist: readthedocs-sphinx-search (==0.3.2) ; extra == "docs"
Requires-Dist: requests (==2.31.0) ; extra == "prodminminion" or extra == "prodmaxminion" or extra == "restconf"
Requires-Dist: rich (==13.7.0) ; extra == "prodminmaster" or extra == "prodmaxmaster"
Requires-Dist: robotframework (==7.0) ; extra == "prodmaxmaster"
Requires-Dist: scrapli (==2023.7.30) ; extra == "prodmaxminion" or extra == "scrapli"
Requires-Dist: scrapli-community (==2023.7.30) ; extra == "prodmaxminion" or extra == "scrapli"
Requires-Dist: scrapli-netconf (==2023.7.30) ; extra == "prodmaxminion" or extra == "netconf"
Requires-Dist: sphinx_rtd_theme (==1.0.0) ; extra == "docs"
Requires-Dist: sphinxcontrib-applehelp (==1.0.1) ; extra == "docs"
Requires-Dist: sphinxcontrib-devhelp (==1.0.1) ; extra == "docs"
Requires-Dist: sphinxcontrib-htmlhelp (==2.0.0) ; extra == "docs"
Requires-Dist: sphinxcontrib-jsmath (==1.0.1) ; extra == "docs"
Requires-Dist: sphinxcontrib-napoleon (==0.7) ; extra == "docs"
Requires-Dist: sphinxcontrib-qthelp (==1.0.2) ; extra == "docs"
Requires-Dist: sphinxcontrib-serializinghtml (==1.1.5) ; extra == "docs"
Requires-Dist: sphinxcontrib-spelling (==7.2.1) ; extra == "docs"
Requires-Dist: tabulate (==0.9.0) ; extra == "prodminmaster" or extra == "prodmaxmaster" or extra == "prodminminion" or extra == "prodmaxminion" or extra == "dataprocessor"
Requires-Dist: textfsm (==1.1.3) ; extra == "prodminminion" or extra == "prodmaxminion"
Requires-Dist: ttp (>=0.9.0,<0.10.0) ; extra == "prodmaxmaster" or extra == "prodminminion" or extra == "prodmaxminion" or extra == "dataprocessor"
Requires-Dist: ttp-templates (>=0.3.0,<0.4.0) ; extra == "prodmaxmaster" or extra == "prodminminion" or extra == "prodmaxminion" or extra == "dataprocessor"
Requires-Dist: xmltodict (==0.13.0) ; extra == "prodminminion" or extra == "prodmaxminion" or extra == "dataprocessor"
Project-URL: Documentation, https://salt-nornir.readthedocs.io/
Project-URL: Repository, https://github.com/dmulyalin/salt-nornir
